document/conf.py
schema_entry/__init__.py
schema_entry/entrypoint.py
schema_entry/entrypoint_base.py
schema_entry/protocol.py
schema_entry/utils.py
schema_entry/version.py
schema_entry-0.2.1.dist-info/LICENSE
schema_entry-0.2.1.dist-info/METADATA
schema_entry-0.2.1.dist-info/WHEEL
schema_entry-0.2.1.dist-info/top_level.txt
schema_entry-0.2.1.dist-info/RECORD
