Metadata-Version: 2.1
Name: schema_entry
Version: 0.2.1
Summary: My package description
Author-email: hsz <hsz1273327@gmail.com>
License: MIT License
Project-URL: changelog, https://github.com/Python-Tools/schema_entry/CHANGELOG.md
Project-URL: documentation, https://github.com/Python-Tools/schema_entry
Project-URL: homepage, https://github.com/Python-Tools/schema_entry
Project-URL: repository, https://github.com/Python-Tools/schema_entry
Keywords: setting-loader,env-loader,commandline-loader,json-schema,validater
Platform: all
Classifier: License :: OSI Approved :: MIT License
Classifier: Programming Language :: Python :: 3
Classifier: Programming Language :: Python :: 3.10
Classifier: Programming Language :: Python :: 3.11
Classifier: Programming Language :: Python :: 3.12
Requires-Python: ~=3.10
License-File: LICENSE
Requires-Dist: jsonschema >=3.2.0
Requires-Dist: pyyaml >=6.0.0
Requires-Dist: mypy >=0.800
Requires-Dist: jsonref >=1.1.0
Provides-Extra: test
Requires-Dist: coverage ; extra == 'test'
Requires-Dist: mypy ; extra == 'test'
Requires-Dist: pycodestyle ; extra == 'test'
Requires-Dist: lxml ; extra == 'test'
Requires-Dist: pydantic ; extra == 'test'
